fluffymodel.py
fluffymodel-0.1.17.dist-info/METADATA
fluffymodel-0.1.17.dist-info/WHEEL
fluffymodel-0.1.17.dist-info/entry_points.txt
fluffymodel-0.1.17.dist-info/RECORD
