Metadata-Version: 2.1
Name: fluffymodel
Version: 0.1.17
Summary: `FluffyModel` is a user-friendly CLI tool designed to seamlessly set up an inference endpoint for open-source ML models. It leverages Gradio and Hugging Face spaces to achieve this.
Author: AvinaashAnandK
Author-email: p17avinaashak@iima.ac.in
Requires-Python: >=3.10,<4.0
Classifier: Programming Language :: Python :: 3
Classifier: Programming Language :: Python :: 3.10
Classifier: Programming Language :: Python :: 3.11
